damy_program/__init__.py
damy_program/dami_randalgo.py
damy_program/question.py
damy_program-0.1.1.dist-info/LICENSE.txt
damy_program-0.1.1.dist-info/WHEEL
damy_program-0.1.1.dist-info/METADATA
damy_program-0.1.1.dist-info/RECORD
