Metadata-Version: 2.1
Name: damy-program
Version: 0.1.1
Summary: 
Author: Your Name
Author-email: you@example.com
Requires-Python: >=3.8,<4.0
Classifier: Programming Language :: Python :: 3
Classifier: Programming Language :: Python :: 3.8
Requires-Dist: python-string-utils (>=1.0.0,<2.0.0)
Requires-Dist: requests (>=2.23.0,<3.0.0)
